DESCRIPTION
LICENSE
MANIFEST.in
README.rst
setup.py
pyScss.egg-info/PKG-INFO
pyScss.egg-info/SOURCES.txt
pyScss.egg-info/dependency_links.txt
pyScss.egg-info/entry_points.txt
pyScss.egg-info/requires.txt
pyScss.egg-info/top_level.txt
scss/__init__.py
scss/__main__.py
scss/_native.py
scss/config.py
scss/cssdefs.py
scss/errors.py
scss/expression.py
scss/rule.py
scss/scss_meta.py
scss/selector.py
scss/setup.py
scss/tool.py
scss/types.py
scss/util.py
scss/functions/__init__.py
scss/functions/core.py
scss/functions/extra.py
scss/functions/library.py
scss/functions/compass/__init__.py
scss/functions/compass/gradients.py
scss/functions/compass/helpers.py
scss/functions/compass/images.py
scss/functions/compass/layouts.py
scss/functions/compass/sprites.py
scss/src/_speedups.c
scss/src/block_locator.c
scss/src/scanner.c