Metadata-Version: 1.0
Name: pyScss
Version: 1.2.0.post2
Summary: pyScss, a Scss compiler for Python
Home-page: http://github.com/Kronuz/pyScss
Author: German M. Bravo (Kronuz)
Author-email: german.mb@gmail.com
License: MIT
Download-URL: http://github.com/Kronuz/pyScss/tarball/v1.2.0.post2
Keywords: css oocss xcss sass scss less precompiler
Platform: UNKNOWN
Classifier: Development Status :: 5 - Production/Stable
Classifier: Intended Audience :: Developers
Classifier: License :: OSI Approved :: MIT License
Classifier: Operating System :: OS Independent
Classifier: Programming Language :: Python
Classifier: Programming Language :: Python :: 3
Classifier: Topic :: Software Development :: Code Generators
Classifier: Topic :: Text Processing :: Markup
Classifier: Topic :: Software Development :: Libraries :: Python Modules
